uP.v
/* Margareth Vela
Carné 19458
Sección: 20
*/
//Program counter
module counter(input wire clk, rst, enable, Load, input wire [11:0] Ld, output reg [11:0] PC);
  always @ (posedge clk, posedge rst) begin
    if (rst)
        PC <= 12'b0;
    else if (Load)
        PC <= Ld;
    else if (enable)
        PC <= PC + 1;
  end
endmodule

//Program ROM
module program_ROM(input wire [11:0] PC, output wire [7:0] program_byte);
  reg [7:0] memory [0:4095];
  initial begin
      $readmemh("memory.list", memory);
  end
  assign program_byte = memory[PC];
endmodule

//Fetch
module FETCH(input wire clk, rst, enable, input wire [7:0] program_byte, output wire [3:0] instr, oprnd);
  FF_D  G1(clk, rst, enable, program_byte[7], instr[3]);
  FF_D  G2(clk, rst, enable, program_byte[6], instr[2]);
  FF_D  G3(clk, rst, enable, program_byte[5], instr[1]);
  FF_D  G4(clk, rst, enable, program_byte[4], instr[0]);
  FF_D  G5(clk, rst, enable, program_byte[3], oprnd[3]);
  FF_D  G6(clk, rst, enable, program_byte[2], oprnd[2]);
  FF_D  G7(clk, rst, enable, program_byte[1], oprnd[1]);
  FF_D  G8(clk, rst, enable, program_byte[0], oprnd[0]);
endmodule

//Bus Driver
module Bus_Driver(input wire enable, input wire [3:0]oprnd, output wire [3:0] data_bus);
  assign data_bus = enable ? oprnd : 4'bz;
endmodule

//Accumulator
module Accumulator(input wire clk, rst, enable, input wire [3:0] d, output reg [3:0] accu);
  always @ (posedge clk, posedge rst, posedge enable) begin
    if(rst) begin
      accu <= 1'b0;
    end
    else if (enable) begin
      accu <= d;
    end
  end
endmodule

//ALU
module alu(input wire [3:0] A, B, input wire [2:0] F, output reg C, Z, output reg [3:0] Y);
  reg [4:0] Y1;

  always @(*) begin
    case(F)
      3'b000:   Y1 = A;
      3'b001:   Y1 = A - B;
      3'b010:   Y1 = B;
      3'b011:   Y1 = A + B;
      3'b100:   Y1 = {1'b0, A ~& B};
      default:  Y1 = 5'b0;
    endcase

    assign Y = Y1[3:0];
    assign C = Y1[4];
    assign Z = ~(Y1[3] | Y1[2] | Y1[1] | Y1[0]);

  end
endmodule

//FF tipo D de 1 bit
module FF_D(input wire clock, reset, enable, d, output reg Y);
  always @ (posedge clock, posedge reset) begin
    if(reset) begin
      Y <= 1'b0;
    end
    else if (enable) begin
      Y <= d;
    end
  end
endmodule

//PHASE
module PHASE(input wire clock, reset, enable, output wire phase);

  FF_D G1(clock, reset, enable, ~phase, phase);

endmodule

//Decoder
module Decoder(input wire [6:0]Address, output reg [12:0]Y);
  always @(Address) begin
    casex(Address)
      7'bxxxx_xx0: Y = 13'b1000_000_001000 ;//caso 1
      7'b0000_1x1: Y = 13'b0100_000_001000 ;//caso 2
      7'b0000_0x1: Y = 13'b1000_000_001000 ;//caso 3
      7'b0001_1x1: Y = 13'b1000_000_001000 ;//caso 4
      7'b0001_0x1: Y = 13'b0100_000_001000 ;//caso 5
      7'b0010_xx1: Y = 13'b0001_001_000010 ;//caso 6
      7'b0011_xx1: Y = 13'b1001_001_100000 ;//caso 7
      7'b0100_xx1: Y = 13'b0011_010_000010 ;//caso 8
      7'b0101_xx1: Y = 13'b0011_010_000100 ;//Caso 9
      7'b0110_xx1: Y = 13'b1011_010_100000 ;//caso 10
      7'b0111_xx1: Y = 13'b1000_000_111000 ;//caso 11
      7'b1000_x11: Y = 13'b0100_000_001000 ;//caso 12
      7'b1000_x01: Y = 13'b1000_000_001000 ;//caso 13
      7'b1001_x11: Y = 13'b1000_000_001000 ;//caso 14
      7'b1001_x01: Y = 13'b0100_000_001000 ;//caso 15
      7'b1010_xx1: Y = 13'b0011_011_000010 ;//caso 16
      7'b1011_xx1: Y = 13'b1011_011_100000 ;//caso 17
      7'b1100_xx1: Y = 13'b0100_000_001000 ;//caso 18
      7'b1101_xx1: Y = 13'b0000_000_001001 ;//caso 19
      7'b1110_xx1: Y = 13'b0011_100_000010 ;//caso 20
      7'b1111_xx1: Y = 13'b1011_100_100000 ;//caso 21
      default:    Y = 13'b1111111111111 ; // caso por default
    endcase
  end
endmodule

//RAM
module RAM(input wire enable, write, read, input wire [11:0]address_RAM, inout [3:0]data);
  reg [3:0] RAM [0:4095];
  reg [3:0]data_out;

  assign data = (enable & read & ~write) ? data_out:4'bz;
  //Escribir en la RAM
  always @ ( address_RAM or data or enable or write ) begin
    if (enable && write) begin
      RAM[address_RAM] = data;
    end
  end
  //Leer de la RAM
  always @ ( address_RAM or enable or write or read) begin
    if (enable && ~write && read) begin
      data_out = RAM[address_RAM];
    end
  end
endmodule

module out(input wire clock, reset, enable,input wire [3:0]d, output wire [3:0] FF_out);
  FF_D  G1(clock, reset, enable, d[3], FF_out[3]);
  FF_D  G2(clock, reset, enable, d[2], FF_out[2]);
  FF_D  G3(clock, reset, enable, d[1], FF_out[1]);
  FF_D  G4(clock, reset, enable, d[0], FF_out[0]);
endmodule

module Flags(input wire clock, reset, enable, C, Z, output wire c_flag, z_flag);
  FF_D  G1(clock, reset, enable, C, c_flag);
  FF_D  G2(clock, reset, enable, Z, z_flag);
endmodule

module uP(input wire clock, reset, input wire [3:0] pushbuttons, output wire phase, c_flag, z_flag, output wire [3:0] instr, oprnd, data_bus, FF_out, accu, output wire [7:0] program_byte, output wire [11:0] PC, address_RAM);

  wire C, Z;
  wire [3:0] ALU_out;
  wire [12:0] control_signals;

  assign  address_RAM = {oprnd, program_byte};

  counter       counter(clock, reset, control_signals[12], control_signals[11], address_RAM, PC);
  program_ROM   program_ROM(PC, program_byte);
  FETCH         FETCH(clock, reset, ~phase, program_byte, instr, oprnd);
  Bus_Driver    Bus_Driver1(control_signals[1], oprnd, data_bus);
  Accumulator   Accumulator(clock, reset, control_signals[10], ALU_out, accu);
  alu           ALU(accu, data_bus, {control_signals[8], control_signals[7], control_signals[6]}, C, Z, ALU_out);
  Bus_Driver    Bus_Driver2(control_signals[3], ALU_out, data_bus);
  PHASE         Phase(clock, reset, 1'b1 , phase);
  Flags         Flags(clock, reset, control_signals[9], C, Z, c_flag, z_flag);
  Decoder       Decode({instr, c_flag, z_flag, phase}, control_signals);
  RAM           RAM(control_signals[5], control_signals[4], control_signals[5], address_RAM, data_bus);
  out           Out(clock, reset, control_signals[0],data_bus, FF_out);
  Bus_Driver    In(control_signals[2], pushbuttons, data_bus);

endmodule

uP_tb.v
/* Margareth Vela
Carné 19458
Sección: 20
*/

module testbench();

  reg clock, reset;
  reg [3:0]pushbuttons;
  wire phase, c_flag, z_flag;
  wire [3:0]instr, oprnd, data_bus, FF_out, accu;
  wire [7:0]program_byte;
  wire [11:0]PC, address_RAM;
  
  uP uP_proyecto(clock, reset, pushbuttons, phase, c_flag, z_flag, instr, oprnd, data_bus, FF_out, accu, program_byte, PC, address_RAM);

  always
    #5 clock <=~clock;

    initial begin
    $display(" \nProyecto Final ");
    $display("clock reset pushbuttons |  phase  c_flag   z_flag   instr   oprnd   data_bus  FF_out   Accu   program_byte       PC          address_RAM ");
    $display("------------------------|----------------------------------------------------------------------------------------------------------------");
    $monitor("%b       %b       %b    |   %b       %b        %b      %b    %b     %b      %b    %b     %b     %b    %b ", clock, reset, pushbuttons, phase, c_flag, z_flag, instr, oprnd, data_bus, FF_out, accu, program_byte, PC, address_RAM);

      reset = 1; clock = 0; pushbuttons = 4'b0;
  #1  reset = 0; pushbuttons = 4'b0110;
  #242 pushbuttons = 4'b1110;
    end

    initial
      #1100 $finish;
    initial begin
        $dumpfile("uP_tb.vcd");
        $dumpvars(0, testbench);
      end
  endmodule

uP_tb.vcd
$date
	Sun Nov 22 14:24:28 2020
$end
$version
	Icarus Verilog
$end
$timescale
	1ps
$end
$scope module testbench $end
$var wire 4 ! data_bus [3:0] $end
$var wire 1 " z_flag $end
$var wire 8 # program_byte [7:0] $end
$var wire 1 $ phase $end
$var wire 4 % oprnd [3:0] $end
$var wire 4 & instr [3:0] $end
$var wire 1 ' c_flag $end
$var wire 12 ( address_RAM [11:0] $end
$var wire 4 ) accu [3:0] $end
$var wire 12 * PC [11:0] $end
$var wire 4 + FF_out [3:0] $end
$var reg 1 , clock $end
$var reg 4 - pushbuttons [3:0] $end
$var reg 1 . reset $end
$scope module uP_proyecto $end
$var wire 1 , clock $end
$var wire 4 / data_bus [3:0] $end
$var wire 4 0 pushbuttons [3:0] $end
$var wire 1 . reset $end
$var wire 1 " z_flag $end
$var wire 8 1 program_byte [7:0] $end
$var wire 1 $ phase $end
$var wire 4 2 oprnd [3:0] $end
$var wire 4 3 instr [3:0] $end
$var wire 13 4 control_signals [12:0] $end
$var wire 1 ' c_flag $end
$var wire 12 5 address_RAM [11:0] $end
$var wire 4 6 accu [3:0] $end
$var wire 1 7 Z $end
$var wire 12 8 PC [11:0] $end
$var wire 4 9 FF_out [3:0] $end
$var wire 1 : C $end
$var wire 4 ; ALU_out [3:0] $end
$scope module ALU $end
$var wire 4 < B [3:0] $end
$var wire 3 = F [2:0] $end
$var wire 4 > A [3:0] $end
$var reg 1 : C $end
$var reg 4 ? Y [3:0] $end
$var reg 5 @ Y1 [4:0] $end
$var reg 1 7 Z $end
$upscope $end
$scope module Accumulator $end
$var wire 1 , clk $end
$var wire 4 A d [3:0] $end
$var wire 1 B enable $end
$var wire 1 . rst $end
$var reg 4 C accu [3:0] $end
$upscope $end
$scope module Bus_Driver1 $end
$var wire 4 D data_bus [3:0] $end
$var wire 1 E enable $end
$var wire 4 F oprnd [3:0] $end
$upscope $end
$scope module Bus_Driver2 $end
$var wire 4 G data_bus [3:0] $end
$var wire 1 H enable $end
$var wire 4 I oprnd [3:0] $end
$upscope $end
$scope module Decode $end
$var wire 7 J Address [6:0] $end
$var reg 13 K Y [12:0] $end
$upscope $end
$scope module FETCH $end
$var wire 1 , clk $end
$var wire 1 L enable $end
$var wire 1 . rst $end
$var wire 8 M program_byte [7:0] $end
$var wire 4 N oprnd [3:0] $end
$var wire 4 O instr [3:0] $end
$scope module G1 $end
$var wire 1 , clock $end
$var wire 1 P d $end
$var wire 1 L enable $end
$var wire 1 . reset $end
$var reg 1 Q Y $end
$upscope $end
$scope module G2 $end
$var wire 1 , clock $end
$var wire 1 R d $end
$var wire 1 L enable $end
$var wire 1 . reset $end
$var reg 1 S Y $end
$upscope $end
$scope module G3 $end
$var wire 1 , clock $end
$var wire 1 T d $end
$var wire 1 L enable $end
$var wire 1 . reset $end
$var reg 1 U Y $end
$upscope $end
$scope module G4 $end
$var wire 1 , clock $end
$var wire 1 V d $end
$var wire 1 L enable $end
$var wire 1 . reset $end
$var reg 1 W Y $end
$upscope $end
$scope module G5 $end
$var wire 1 , clock $end
$var wire 1 X d $end
$var wire 1 L enable $end
$var wire 1 . reset $end
$var reg 1 Y Y $end
$upscope $end
$scope module G6 $end
$var wire 1 , clock $end
$var wire 1 Z d $end
$var wire 1 L enable $end
$var wire 1 . reset $end
$var reg 1 [ Y $end
$upscope $end
$scope module G7 $end
$var wire 1 , clock $end
$var wire 1 \ d $end
$var wire 1 L enable $end
$var wire 1 . reset $end
$var reg 1 ] Y $end
$upscope $end
$scope module G8 $end
$var wire 1 , clock $end
$var wire 1 ^ d $end
$var wire 1 L enable $end
$var wire 1 . reset $end
$var reg 1 _ Y $end
$upscope $end
$upscope $end
$scope module Flags $end
$var wire 1 : C $end
$var wire 1 7 Z $end
$var wire 1 , clock $end
$var wire 1 ` enable $end
$var wire 1 . reset $end
$var wire 1 " z_flag $end
$var wire 1 ' c_flag $end
$scope module G1 $end
$var wire 1 , clock $end
$var wire 1 : d $end
$var wire 1 ` enable $end
$var wire 1 . reset $end
$var reg 1 ' Y $end
$upscope $end
$scope module G2 $end
$var wire 1 , clock $end
$var wire 1 7 d $end
$var wire 1 ` enable $end
$var wire 1 . reset $end
$var reg 1 " Y $end
$upscope $end
$upscope $end
$scope module In $end
$var wire 4 a data_bus [3:0] $end
$var wire 1 b enable $end
$var wire 4 c oprnd [3:0] $end
$upscope $end
$scope module Out $end
$var wire 1 , clock $end
$var wire 4 d d [3:0] $end
$var wire 1 e enable $end
$var wire 1 . reset $end
$var wire 4 f FF_out [3:0] $end
$scope module G1 $end
$var wire 1 , clock $end
$var wire 1 g d $end
$var wire 1 e enable $end
$var wire 1 . reset $end
$var reg 1 h Y $end
$upscope $end
$scope module G2 $end
$var wire 1 , clock $end
$var wire 1 i d $end
$var wire 1 e enable $end
$var wire 1 . reset $end
$var reg 1 j Y $end
$upscope $end
$scope module G3 $end
$var wire 1 , clock $end
$var wire 1 k d $end
$var wire 1 e enable $end
$var wire 1 . reset $end
$var reg 1 l Y $end
$upscope $end
$scope module G4 $end
$var wire 1 , clock $end
$var wire 1 m d $end
$var wire 1 e enable $end
$var wire 1 . reset $end
$var reg 1 n Y $end
$upscope $end
$upscope $end
$scope module Phase $end
$var wire 1 , clock $end
$var wire 1 o enable $end
$var wire 1 . reset $end
$var wire 1 $ phase $end
$scope module G1 $end
$var wire 1 , clock $end
$var wire 1 p d $end
$var wire 1 o enable $end
$var wire 1 . reset $end
$var reg 1 $ Y $end
$upscope $end
$upscope $end
$scope module RAM $end
$var wire 12 q address_RAM [11:0] $end
$var wire 4 r data [3:0] $end
$var wire 1 s enable $end
$var wire 1 t read $end
$var wire 1 u write $end
$var reg 4 v data_out [3:0] $end
$upscope $end
$scope module counter $end
$var wire 12 w Ld [11:0] $end
$var wire 1 x Load $end
$var wire 1 , clk $end
$var wire 1 y enable $end
$var wire 1 . rst $end
$var reg 12 z PC [11:0] $end
$upscope $end
$scope module program_ROM $end
$var wire 12 { PC [11:0] $end
$var wire 8 | program_byte [7:0] $end
$upscope $end
$upscope $end
$upscope $end
$enddefinitions $end
#0
$dumpvars
b1001111 |
b0 {
b0 z
1y
0x
b1001111 w
bx v
0u
0t
0s
b0 r
b1001111 q
1p
1o
0n
0m
0l
0k
0j
0i
0h
0g
b0 f
0e
b0 d
b0 c
0b
b0 a
0`
0_
1^
0]
1\
0[
1Z
0Y
1X
0W
0V
0U
0T
0S
1R
0Q
0P
b0 O
b0 N
b1001111 M
1L
b1000000001000 K
b0 J
b0 I
1H
b0 G
b0 F
0E
b0 D
b0 C
0B
b0 A
b0 @
b0 ?
b0 >
b0 =
b0 <
b0 ;
0:
b0 9
b0 8
17
b0 6
b1001111 5
b1000000001000 4
b0 3
b0 2
b1001111 1
b0 0
b0 /
1.
b0 -
0,
b0 +
b0 *
b0 )
b1001111 (
0'
b0 &
b0 %
0$
b1001111 #
0"
b0 !
$end
#1
b110 -
b110 0
b110 c
0.
#5
1g
1i
1k
1m
07
b1111 ;
b1111 ?
b1111 A
b1111 I
b1111 @
b1111 !
b1111 /
b1111 <
b1111 D
b1111 G
b1111 a
b1111 d
b1111 r
1`
0H
b10 =
1B
1E
0y
0p
0L
b11010000010 4
b11010000010 K
1V
1P
1$
1_
1]
1[
b1111 %
b1111 2
b1111 F
b1111 N
1Y
b100001 J
b100 &
b100 3
b100 O
1S
b111111011111 (
b111111011111 5
b111111011111 q
b111111011111 w
b11011111 #
b11011111 1
b11011111 M
b11011111 |
b1 *
b1 8
b1 z
b1 {
1,
#10
0,
#15
b1111 !
b1111 /
b1111 <
b1111 D
b1111 G
b1111 a
b1111 d
b1111 r
0`
1H
b0 =
0B
0E
1y
1p
b1000000001000 4
b1000000001000 K
1L
b1111 )
b1111 6
b1111 >
b1111 C
b100000 J
0$
1,
#20
0,
#25
1e
0y
0p
0L
b1001 4
b1001 K
0\
0Z
0X
0P
1$
1W
b1101001 J
b1101 &
b1101 3
b1101 O
1Q
b111101010001 (
b111101010001 5
b111101010001 q
b111101010001 w
b1010001 #
b1010001 1
b1010001 M
b1010001 |
b10 *
b10 8
b10 z
b10 {
1,
#30
0,
#35
0e
1y
1p
b1000000001000 4
b1000000001000 K
1L
b1101000 J
0$
1h
1j
1l
b1111 +
b1111 9
b1111 f
1n
1,
#40
0,
#45
b110 ;
b110 ?
b110 A
b110 I
b110 @
0g
0m
b110 !
b110 /
b110 <
b110 D
b110 G
b110 a
b110 d
b110 r
1b
1`
0H
b10 =
1B
0y
0p
0L
b11010000100 4
b11010000100 K
0^
0V
1$
0]
0[
b1 %
b1 2
b1 F
b1 N
0Y
b101001 J
b101 &
b101 3
b101 O
0Q
b101000000 (
b101000000 5
b101000000 q
b101000000 w
b1000000 #
b1000000 1
b1000000 M
b1000000 |
b11 *
b11 8
b11 z
b11 {
1,
#50
0,
#55
0b
0`
1H
b0 =
0B
1y
1p
b1000000001000 4
b1000000001000 K
1L
b110 )
b110 6
b110 >
b110 C
b101000 J
0$
1,
#60
0,
#65
0i
0k
17
b0 ;
b0 ?
b0 A
b0 I
b0 @
b0 !
b0 /
b0 <
b0 D
b0 G
b0 a
b0 d
b0 r
1`
0H
b10 =
1B
1E
0y
0p
0L
b11010000010 4
b11010000010 K
1^
1\
1Z
1X
1$
b0 %
b0 2
b0 F
b0 N
0_
b100001 J
b100 &
b100 3
b100 O
0W
b1001111 (
b1001111 5
b1001111 q
b1001111 w
b1001111 #
b1001111 1
b1001111 M
b1001111 |
b100 *
b100 8
b100 z
b100 {
1,
#70
0,
#75
b0 !
b0 /
b0 <
b0 D
b0 G
b0 a
b0 d
b0 r
0`
1H
b0 =
0B
0E
1y
1p
1L
b1000000001000 4
b1000000001000 K
b0 )
b0 6
b0 >
b0 C
0$
b100010 J
1"
1,
#80
0,
#85
1g
1i
1k
1m
07
b1111 ;
b1111 ?
b1111 A
b1111 I
b1111 @
b1111 !
b1111 /
b1111 <
b1111 D
b1111 G
b1111 a
b1111 d
b1111 r
1`
0H
b10 =
1B
1E
0y
0p
b11010000010 4
b11010000010 K
0L
0^
0Z
1T
0R
1P
b100011 J
1$
1_
1]
1[
b1111 %
b1111 2
b1111 F
b1111 N
1Y
b111110101010 (
b111110101010 5
b111110101010 q
b111110101010 w
b10101010 #
b10101010 1
b10101010 M
b10101010 |
b101 *
b101 8
b101 z
b101 {
1,
#90
0,
#95
b1111 !
b1111 /
b1111 <
b1111 D
b1111 G
b1111 a
b1111 d
b1111 r
0`
1H
b0 =
0B
0E
1y
1p
1L
b1000000001000 4
b1000000001000 K
b1111 )
b1111 6
b1111 >
b1111 C
0$
b100000 J
0"
1,
#100
0,
#105
0i
0m
07
1:
b1001 ;
b1001 ?
b1001 A
b1001 I
b11001 @
b1010 !
b1010 /
b1010 <
b1010 D
b1010 G
b1010 a
b1010 d
b1010 r
1`
0H
b11 =
1B
1E
0y
0p
0L
b11011000010 4
b11011000010 K
0\
0P
1$
0_
b1010 %
b1010 2
b1010 F
b1010 N
0[
1U
0S
b1010001 J
b1010 &
b1010 3
b1010 O
1Q
b101000101000 (
b101000101000 5
b101000101000 q
b101000101000 w
b101000 #
b101000 1
b101000 M
b101000 |
b110 *
b110 8
b110 z
b110 {
1,
#110
0,
#115
0k
1m
0:
b1001 !
b1001 /
b1001 <
b1001 D
b1001 G
b1001 a
b1001 d
b1001 r
0`
1H
b0 =
0B
0E
1y
b1001 ;
b1001 ?
b1001 A
b1001 I
b1001 @
1p
1L
b1000000001000 4
b1000000001000 K
b1001 )
b1001 6
b1001 >
b1001 C
0$
b1010100 J
1'
1,
#120
0,
#125
0m
07
0:
b1 ;
b1 ?
b1 A
b1 I
b1 @
b1000 !
b1000 /
b1000 <
b1000 D
b1000 G
b1000 a
b1000 d
b1000 r
1`
0H
b1 =
1E
0y
0p
0L
b1001000010 4
b1001000010 K
1\
0T
1R
1$
b1000 %
b1000 2
b1000 F
b1000 N
0]
b10101 J
b10 &
b10 3
b10 O
0Q
b100001001010 (
b100001001010 5
b100001001010 q
b100001001010 w
b1001010 #
b1001010 1
b1001010 M
b1001010 |
b111 *
b111 8
b111 z
b111 {
1,
#130
0,
#135
1m
b1001 ;
b1001 ?
b1001 A
b1001 I
b1001 @
b1001 !
b1001 /
b1001 <
b1001 D
b1001 G
b1001 a
b1001 d
b1001 r
0`
1H
b0 =
0E
1y
1p
1L
b1000000001000 4
b1000000001000 K
0$
b10000 J
0'
1,
#140
0,
#145
1k
0m
b1010 ;
b1010 ?
b1010 A
b1010 I
b1010 @
b1010 !
b1010 /
b1010 <
b1010 D
b1010 G
b1010 a
b1010 d
b1010 r
1`
0H
b10 =
1B
1E
0y
0p
0L
b11010000010 4
b11010000010 K
0\
1Z
1T
0R
1$
b1010 %
b1010 2
b1010 F
b1010 N
1]
0U
b100001 J
b100 &
b100 3
b100 O
1S
b101000101100 (
b101000101100 5
b101000101100 q
b101000101100 w
b101100 #
b101100 1
b101100 M
b101100 |
b1000 *
b1000 8
b1000 z
b1000 {
1,
#150
0,
#155
b1010 !
b1010 /
b1010 <
b1010 D
b1010 G
b1010 a
b1010 d
b1010 r
0`
1H
b0 =
0B
0E
1y
1p
b1000000001000 4
b1000000001000 K
1L
b1010 )
b1010 6
b1010 >
b1010 C
b100000 J
0$
1,
#160
0,
#165
1i
0k
07
1:
b1110 ;
b1110 ?
b1110 A
b1110 I
b11110 @
b1100 !
b1100 /
b1100 <
b1100 D
b1100 G
b1100 a
b1100 d
b1100 r
1`
0H
b1 =
1E
0y
0p
0L
b1001000010 4
b1001000010 K
1^
0Z
0X
1P
1$
0]
b1100 %
b1100 2
b1100 F
b1100 N
1[
1U
b10001 J
b10 &
b10 3
b10 O
0S
b110010100001 (
b110010100001 5
b110010100001 q
b110010100001 w
b10100001 #
b10100001 1
b10100001 M
b10100001 |
b1001 *
b1001 8
b1001 z
b1001 {
1,
#170
0,
#175
0i
1k
0:
b1010 ;
b1010 ?
b1010 A
b1010 I
b1010 @
b1010 !
b1010 /
b1010 <
b1010 D
b1010 G
b1010 a
b1010 d
b1010 r
0`
1H
b0 =
0E
1y
1p
1L
b1000000001000 4
b1000000001000 K
0$
b10100 J
1'
1,
#180
0,
#185
0g
0k
1m
07
0:
b1011 ;
b1011 ?
b1011 A
b1011 I
b1011 @
b1 !
b1 /
b1 <
b1 D
b1 G
b1 a
b1 d
b1 r
1`
0H
b11 =
1B
1E
0y
0p
0L
b11011000010 4
b11011000010 K
1\
1X
1R
1$
1_
0[
b1 %
b1 2
b1 F
b1 N
0Y
b1010101 J
b1010 &
b1010 3
b1010 O
1Q
b111101011 (
b111101011 5
b111101011 q
b111101011 w
b11101011 #
b11101011 1
b11101011 M
b11101011 |
b1010 *
b1010 8
b1010 z
b1010 {
1,
#190
0,
#195
1g
1k
b1011 !
b1011 /
b1011 <
b1011 D
b1011 G
b1011 a
b1011 d
b1011 r
0`
1H
b0 =
0B
0E
1y
b1011 ;
b1011 ?
b1011 A
b1011 I
b1011 @
1p
1L
b1000000001000 4
b1000000001000 K
b1011 )
b1011 6
b1011 >
b1011 C
0$
b1010000 J
0'
1,
#200
0,
#205
b100 ;
b100 ?
b100 A
b100 I
b100 @
1`
0H
b100 =
1B
1E
0y
0p
0L
b11100000010 4
b11100000010 K
0^
0\
0X
1V
0T
1$
1]
b1011 %
b1011 2
b1011 F
b1011 N
1Y
b1110001 J
b1110 &
b1110 3
b1110 O
1S
b101111010000 (
b101111010000 5
b101111010000 q
b101111010000 w
b11010000 #
b11010000 1
b11010000 M
b11010000 |
b1011 *
b1011 8
b1011 z
b1011 {
1,
#210
0,
#215
0g
1i
0k
0m
b100 !
b100 /
b100 <
b100 D
b100 G
b100 a
b100 d
b100 r
0`
1H
b0 =
0B
0E
1y
b100 ;
b100 ?
b100 A
b100 I
b100 @
1p
b1000000001000 4
b1000000001000 K
1L
b100 )
b100 6
b100 >
b100 C
b1110000 J
0$
1,
#220
0,
#225
1e
0y
0p
0L
b1001 4
b1001 K
0P
1$
0_
0]
b0 %
b0 2
b0 F
b0 N
0Y
1W
b1101001 J
b1101 &
b1101 3
b1101 O
0U
b1010000 (
b1010000 5
b1010000 q
b1010000 w
b1010000 #
b1010000 1
b1010000 M
b1010000 |
b1100 *
b1100 8
b1100 z
b1100 {
1,
#230
0,
#235
0e
1y
1p
b1000000001000 4
b1000000001000 K
1L
b1101000 J
0$
0h
0l
b100 +
b100 9
b100 f
0n
1,
#240
0,
#243
b1110 -
b1110 0
b1110 c
#245
b1110 ;
b1110 ?
b1110 A
b1110 I
b1110 @
1g
1k
b1110 !
b1110 /
b1110 <
b1110 D
b1110 G
b1110 a
b1110 d
b1110 r
1b
1`
0H
b10 =
1B
0y
0p
0L
b11010000100 4
b11010000100 K
1T
1$
b101001 J
b101 &
b101 3
b101 O
0Q
b1110000 (
b1110000 5
b1110000 q
b1110000 w
b1110000 #
b1110000 1
b1110000 M
b1110000 |
b1101 *
b1101 8
b1101 z
b1101 {
1,
#250
0,
#255
0b
0`
1H
b0 =
0B
1y
1p
b1000000001000 4
b1000000001000 K
1L
b1110 )
b1110 6
b1110 >
b1110 C
b101000 J
0$
1,
#260
0,
#265
1t
1u
1s
0p
0L
b1000000111000 4
b1000000111000 K
0V
0T
0R
1$
b111001 J
b111 &
b111 3
b111 O
1U
b0 (
b0 5
b0 q
b0 w
b0 #
b0 1
b0 M
b0 |
b1110 *
b1110 8
b1110 z
b1110 {
1,
#270
0,
#275
0t
0u
0s
1^
1\
1Z
1X
1R
1p
b1000000001000 4
b1000000001000 K
1L
b1001111 (
b1001111 5
b1001111 q
b1001111 w
b1001111 #
b1001111 1
b1001111 M
b1001111 |
b1111 *
b1111 8
b1111 z
b1111 {
b111000 J
0$
1,
#280
0,
#285
1m
b1111 ;
b1111 ?
b1111 A
b1111 I
b1111 @
b1111 !
b1111 /
b1111 <
b1111 D
b1111 G
b1111 a
b1111 d
b1111 r
1`
0H
b10 =
1B
1E
0y
0p
0L
b11010000010 4
b11010000010 K
0\
0Z
0X
1V
1T
1$
1_
1]
1[
b1111 %
b1111 2
b1111 F
b1111 N
1Y
0W
b100001 J
b100 &
b100 3
b100 O
0U
b111101110001 (
b111101110001 5
b111101110001 q
b111101110001 w
b1110001 #
b1110001 1
b1110001 M
b1110001 |
b10000 *
b10000 8
b10000 z
b10000 {
1,
#290
0,
#295
b1111 !
b1111 /
b1111 <
b1111 D
b1111 G
b1111 a
b1111 d
b1111 r
0`
1H
b0 =
0B
0E
1y
1p
b1000000001000 4
b1000000001000 K
1L
b1111 )
b1111 6
b1111 >
b1111 C
b100000 J
0$
1,
#300
0,
#305
1t
1u
1s
0p
0L
b1000000111000 4
b1000000111000 K
0T
0R
1$
0]
0[
b1 %
b1 2
b1 F
b1 N
0Y
1W
b111001 J
b111 &
b111 3
b111 O
1U
b100010001 (
b100010001 5
b100010001 q
b100010001 w
b10001 #
b10001 1
b10001 M
b10001 |
b10001 *
b10001 8
b10001 z
b10001 {
1,
#310
0,
#315
0t
0u
0s
0^
1\
1X
0V
1R
1p
b1000000001000 4
b1000000001000 K
1L
b101001010 (
b101001010 5
b101001010 q
b101001010 w
b1001010 #
b1001010 1
b1001010 M
b1001010 |
b10010 *
b10010 8
b10010 z
b10010 {
b111000 J
0$
1,
#320
0,
#325
0i
0m
b1010 ;
b1010 ?
b1010 A
b1010 I
b1010 @
b1010 !
b1010 /
b1010 <
b1010 D
b1010 G
b1010 a
b1010 d
b1010 r
1`
0H
b10 =
1B
1E
0y
0p
0L
b11010000010 4
b11010000010 K
0X
1V
1T
1$
0_
1]
b1010 %
b1010 2
b1010 F
b1010 N
1Y
0W
b100001 J
b100 &
b100 3
b100 O
0U
b101001110010 (
b101001110010 5
b101001110010 q
b101001110010 w
b1110010 #
b1110010 1
b1110010 M
b1110010 |
b10011 *
b10011 8
b10011 z
b10011 {
1,
#330
0,
#335
b1010 !
b1010 /
b1010 <
b1010 D
b1010 G
b1010 a
b1010 d
b1010 r
0`
1H
b0 =
0B
0E
1y
1p
b1000000001000 4
b1000000001000 K
1L
b1010 )
b1010 6
b1010 >
b1010 C
b100000 J
0$
1,
#340
0,
#345
1t
1u
1s
0p
0L
b1000000111000 4
b1000000111000 K
0V
0R
1$
b10 %
b10 2
b10 F
b10 N
0Y
1W
b111001 J
b111 &
b111 3
b111 O
1U
b1000100010 (
b1000100010 5
b1000100010 q
b1000100010 w
b100010 #
b100010 1
b100010 M
b100010 |
b10100 *
b10100 8
b10100 z
b10100 {
1,
#350
0,
#355
0t
0u
0s
1^
0\
0T
1R
1p
b1000000001000 4
b1000000001000 K
1L
b1001000001 (
b1001000001 5
b1001000001 q
b1001000001 w
b1000001 #
b1000001 1
b1000001 M
b1000001 |
b10101 *
b10101 8
b10101 z
b10101 {
b111000 J
0$
1,
#360
0,
#365
0g
0k
1m
07
b1 ;
b1 ?
b1 A
b1 I
b1 @
b1 !
b1 /
b1 <
b1 D
b1 G
b1 a
b1 d
b1 r
1`
0H
b10 =
1B
1E
0y
0p
0L
b11010000010 4
b11010000010 K
1\
1V
1T
1$
1_
b1 %
b1 2
b1 F
b1 N
0]
0W
b100001 J
b100 &
b100 3
b100 O
0U
b101110011 (
b101110011 5
b101110011 q
b101110011 w
b1110011 #
b1110011 1
b1110011 M
b1110011 |
b10110 *
b10110 8
b10110 z
b10110 {
1,
#370
0,
#375
b1 !
b1 /
b1 <
b1 D
b1 G
b1 a
b1 d
b1 r
0`
1H
b0 =
0B
0E
1y
1p
b1000000001000 4
b1000000001000 K
1L
b1 )
b1 6
b1 >
b1 C
b100000 J
0$
1,
#380
0,
#385
1t
1u
1s
0p
0L
b1000000111000 4
b1000000111000 K
0R
1$
b11 %
b11 2
b11 F
b11 N
1]
1W
b111001 J
b111 &
b111 3
b111 O
1U
b1100110011 (
b1100110011 5
b1100110011 q
b1100110011 w
b110011 #
b110011 1
b110011 M
b110011 |
b10111 *
b10111 8
b10111 z
b10111 {
1,
#390
0,
#395
0t
0u
0s
0^
0\
0V
1R
1p
b1000000001000 4
b1000000001000 K
1L
b1101100000 (
b1101100000 5
b1101100000 q
b1101100000 w
b1100000 #
b1100000 1
b1100000 M
b1100000 |
b11000 *
b11000 8
b11000 z
b11000 {
b111000 J
0$
1,
